anticp3/__init__.py
anticp3/anticp3.py
anticp3/example.fasta
anticp3/db/anticp3.pdb
anticp3/db/anticp3.phr
anticp3/db/anticp3.pin
anticp3/db/anticp3.pot
anticp3/db/anticp3.psq
anticp3/db/anticp3.ptf
anticp3/db/anticp3.pto
anticp3/model/ESM2-t33.json
anticp3/ncbi_blast_2.15/BLAST_PRIVACY
anticp3/ncbi_blast_2.15/ChangeLog
anticp3/ncbi_blast_2.15/LICENSE
anticp3/ncbi_blast_2.15/bin/blastp
anticp3-1.1.1.dist-info/licenses/LICENSE
anticp3-1.1.1.dist-info/METADATA
anticp3-1.1.1.dist-info/WHEEL
anticp3-1.1.1.dist-info/entry_points.txt
anticp3-1.1.1.dist-info/top_level.txt
anticp3-1.1.1.dist-info/RECORD
