Metadata-Version: 2.4
Name: anticp3
Version: 1.1.1
Summary: Prediction of Anticancer Proteins using Finetuned ESM2 and BLAST
Author-email: "G.P.S Raghava" <raghava@iiitd.ac.in>
License:                     GNU GENERAL PUBLIC LICENSE
Requires-Python: >=3.8
License-File: LICENSE
Requires-Dist: transformers
Requires-Dist: safetensors
Requires-Dist: torch
Requires-Dist: biopython
Requires-Dist: pandas
Requires-Dist: tqdm
Requires-Dist: colorama
Dynamic: license-file
